cutekit/__init__.py
cutekit/__main__.py
cutekit/builder.py
cutekit/cli.py
cutekit/const.py
cutekit/doc.py
cutekit/export.py
cutekit/fmt.py
cutekit/jexpr.py
cutekit/mixins.py
cutekit/model.py
cutekit/ninja.py
cutekit/package.py
cutekit/plugins.py
cutekit/py.typed
cutekit/requirements.txt
cutekit/rules.py
cutekit/shell.py
cutekit/utils.py
cutekit/vt100.py
cutekit-0.10.7.dist-info/METADATA
cutekit-0.10.7.dist-info/WHEEL
cutekit-0.10.7.dist-info/entry_points.txt
cutekit-0.10.7.dist-info/top_level.txt
cutekit-0.10.7.dist-info/RECORD
