Metadata-Version: 2.4
Name: cutekit
Version: 0.10.7
Summary: The magical build system and package manager
Author-email: Keyboard Slayer <joda@cute.engineering>, Sleepy Monax <nivb@cute.engineering>, Cyp <cypb@cute.engineering>, Cute Engineering <contact@cute.engineering>
License: MIT
Requires-Python: >=3.11
Requires-Dist: graphviz~=0.20.1
Requires-Dist: dataclasses-json~=0.6.4
